atheon_codex/__init__.py
atheon_codex/_internals.py
atheon_codex/_utils.py
atheon_codex/async_client.py
atheon_codex/client.py
atheon_codex/exceptions.py
atheon_codex/models.py
atheon_codex-0.5.0.dist-info/METADATA
atheon_codex-0.5.0.dist-info/WHEEL
atheon_codex-0.5.0.dist-info/licenses/LICENSE.md
atheon_codex-0.5.0.dist-info/RECORD
