Metadata-Version: 2.4
Name: atheon-codex
Version: 0.5.0
Summary: Python SDK for Atheon
Project-URL: homepage, https://atheon.ad/
Project-URL: repository, https://github.com/atheon-inc/atheon-codex
Project-URL: documentation, https://github.com/atheon-inc/atheon-codex
Author-email: Saurabh Ghanekar <ghanekarsaurabh8@gmail.com>
License-Expression: Apache-2.0
License-File: LICENSE.md
Requires-Python: >=3.10
Requires-Dist: httpx>=0.28
Requires-Dist: pydantic>=2.10
